gfat/__init__.py
gfat/cli.py
gfat/gfat.py
gfat-0.1.1.dist-info/DESCRIPTION.rst
gfat-0.1.1.dist-info/METADATA
gfat-0.1.1.dist-info/RECORD
gfat-0.1.1.dist-info/WHEEL
gfat-0.1.1.dist-info/entry_points.txt
gfat-0.1.1.dist-info/metadata.json
gfat-0.1.1.dist-info/top_level.txt
