Metadata-Version: 2.0
Name: gfat
Version: 0.1.1
Summary: Generador Ficheros Agencia Tributaria
Home-page: https://github.com/paurosello/gfat
Author: Pau Rosello Van Schoor
Author-email: paurosello@gmail.com
License: MIT license
Keywords: gfat
Platform: UNKNOWN
Classifier: Development Status :: 2 - Pre-Alpha
Classifier: Intended Audience :: Developers
Classifier: License :: OSI Approved :: MIT License
Classifier: Natural Language :: English
Classifier: Programming Language :: Python :: 2
Classifier: Programming Language :: Python :: 2.6
Classifier: Programming Language :: Python :: 2.7
Classifier: Programming Language :: Python :: 3
Classifier: Programming Language :: Python :: 3.3
Classifier: Programming Language :: Python :: 3.4
Classifier: Programming Language :: Python :: 3.5
Requires-Dist: Click (>=6.0)
